shapecheck/__init__.py
shapecheck/_main.py
shapecheck/exception.py
shapecheck/py.typed
shapecheck/shapecheck.py
shapecheck/utils.py
shapecheck-0.0.2.dist-info/LICENSE
shapecheck-0.0.2.dist-info/METADATA
shapecheck-0.0.2.dist-info/WHEEL
shapecheck-0.0.2.dist-info/top_level.txt
shapecheck-0.0.2.dist-info/zip-safe
shapecheck-0.0.2.dist-info/RECORD
