Metadata-Version: 2.1
Name: shapecheck
Version: 0.0.2
Summary: Framework-agnostic library for checking array shapes at runtime.
Home-page: https://github.com/n2cholas/shapecheck
Author: Nicholas Vadivelu
Author-email: nicholas.vadivelu@gmail.com
License: MIT
Platform: UNKNOWN
